pmotif_lib/__init__.py
pmotif_lib/graphlet_occurence.py
pmotif_lib/graphlet_representation.py
pmotif_lib/p_motif_graph.py
pmotif_lib/randomization.py
pmotif_lib/result_transformer.py
pmotif_lib/gtrieScanner/__init__.py
pmotif_lib/gtrieScanner/graph_io.py
pmotif_lib/gtrieScanner/parsing.py
pmotif_lib/gtrieScanner/wrapper.py
pmotif_lib/p_metric/__init__.py
pmotif_lib/p_metric/metric_consolidation.py
pmotif_lib/p_metric/metric_processing.py
pmotif_lib/p_metric/p_anchor_node_distance.py
pmotif_lib/p_metric/p_degree.py
pmotif_lib/p_metric/p_graph_module_participation.py
pmotif_lib/p_metric/p_metric.py
pmotif_lib/p_metric/p_metric_result.py
pmotif_lib-1.0.2.dist-info/METADATA
pmotif_lib-1.0.2.dist-info/WHEEL
pmotif_lib-1.0.2.dist-info/licenses/LICENSE
pmotif_lib-1.0.2.dist-info/RECORD
