Metadata-Version: 2.1
Name: pmotif_lib
Version: 1.0.2
Summary: Perform motif detection, either with traditional frequency, or with positional metrics for each graphlet occurrence.
Project-URL: Homepage, https://github.com/timgarrels/pmotif_lib
Project-URL: documentation, https://github.com/timgarrels/pmotif_lib/wiki
Project-URL: Bug Tracker, https://github.com/timgarrels/pmotif_lib/issues
Project-URL: Repository, https://github.com/timgarrels/pmotif_lib
Author-email: Tim Garrels <tim.garrels@protonmail.com>
License-File: LICENSE
Classifier: License :: OSI Approved :: MIT License
Classifier: Operating System :: OS Independent
Classifier: Programming Language :: Python :: 3
Requires-Python: >=3.7
Requires-Dist: networkx==3.1
Requires-Dist: pandas==2.0.0
Requires-Dist: scipy==1.10.1
Requires-Dist: tqdm==4.65.0
